extrabol/__init__.py
extrabol/extrabol.py
extrabol/example/SN2010bc.snana.dat
extrabol/filter_data/__init__.py
extrabol/filter_data/fps.xml
extrabol/template_bank/smoothed_sn1a.npz
extrabol/template_bank/smoothed_sn1bc.npz
extrabol/template_bank/smoothed_sn2l.npz
extrabol/template_bank/smoothed_sn2p.npz
extrabol-1.2.1.dist-info/LICENSE
extrabol-1.2.1.dist-info/METADATA
extrabol-1.2.1.dist-info/WHEEL
extrabol-1.2.1.dist-info/entry_points.txt
extrabol-1.2.1.dist-info/top_level.txt
extrabol-1.2.1.dist-info/RECORD
