Metadata-Version: 2.1
Name: extrabol
Version: 1.2.1
Summary: Estimate SN bolometric light curves
Author: Ian M. Thornton, Sebastian Gomez, Griffin Hosseinzadeh
Author-email: "V. Ashley Villar" <ashleyvillar@cfa.harvard.edu>
Project-URL: Repository, https://github.com/villrv/extrabol
Project-URL: Documentation, https://extrabol.readthedocs.io/en/latest/
Classifier: Programming Language :: Python :: 3
Classifier: License :: OSI Approved :: MIT License
Classifier: Operating System :: OS Independent
Requires-Python: >=3.6
License-File: LICENSE
Requires-Dist: numpy
Requires-Dist: astropy
Requires-Dist: matplotlib
Requires-Dist: george
Requires-Dist: extinction
Requires-Dist: emcee
Requires-Dist: mkdocs >=1.2.2
Requires-Dist: importlib-resources
